retarus/__init__.py
retarus/version.py
retarus/common/__init__.py
retarus/common/config.py
retarus/common/exceptions.py
retarus/common/region.py
retarus/common/transport.py
retarus/common/utils.py
retarus/fax/__init__.py
retarus/fax/_async.py
retarus/fax/client.py
retarus/fax/model.py
retarus/fax/sync.py
retarus/sms/__init__.py
retarus/sms/_async.py
retarus/sms/client.py
retarus/sms/model.py
retarus/sms/sync.py
retarus/webexpress/_async.py
retarus/webexpress/client.py
retarus/webexpress/models.py
retarus/webexpress/sync.py
retarus-0.2.0.dist-info/LICENSE
retarus-0.2.0.dist-info/METADATA
retarus-0.2.0.dist-info/WHEEL
retarus-0.2.0.dist-info/top_level.txt
retarus-0.2.0.dist-info/RECORD
