Metadata-Version: 2.1
Name: retarus
Version: 0.2.0
Summary: The official client SDK for easy implementation of Retarus messaging services.
Home-page: https://github.com/retarus/retarus-python
Author: Retarus GmbH
Author-email: michael.lichtenecker@retarus.de
License-File: LICENSE
Requires-Dist: aiohttp
Requires-Dist: aiohttp-retry
Requires-Dist: pydantic
Requires-Dist: requests
